{
  "strategy": "Golden Stocks",
  "summary": {
    "initial_capital": 1000000,
    "final_capital": 1015434.93309021,
    "net_profit": 15434.933090209961,
    "total_return_percent": 1.5434933090209961,
    "total_trades": 12,
    "winning_trades": 5,
    "losing_trades": 7,
    "win_rate": 41.66666666666667,
    "avg_holding_days": 21.416666666666668,
    "target_hits": 0,
    "stoploss_hits": 1,
    "breakeven_hits": 1
  },
  "all_trades": [
    {
      "symbol": "APLAPOLLO",
      "company_name": "APL Apollo Tubes Ltd.",
      "category": "Golden Stock",
      "entry_price": 1890.5999755859375,
      "entry_date": "2026-04-07 00:00:00+05:30",
      "trendline_price": 1877.066650390625,
      "shares": 43,
      "position_value": 81295.79895019531,
      "target_price": 2268.719970703125,
      "stoploss_price": 1890.5999755859375,
      "status": "closed",
      "highest_price": 2143.89990234375,
      "exit_price": 1873.0,
      "exit_date": "2026-05-04 00:00:00+05:30",
      "exit_value": 80539.0,
      "profit_loss": -756.7989501953125,
      "profit_loss_percent": -0.9309201212955105,
      "exit_reason": "Breakeven Stop Hit",
      "holding_days": 27
    },
    {
      "symbol": "DMART",
      "company_name": "Avenue Supermarts Ltd.",
      "category": "Golden Stock",
      "entry_price": 4589.39990234375,
      "entry_date": "2026-04-21 00:00:00+05:30",
      "trendline_price": 4556.783610026042,
      "shares": 12,
      "position_value": 55072.798828125,
      "target_price": 5507.2798828125,
      "stoploss_price": 4222.24791015625,
      "status": "closed",
      "highest_price": 4594.7998046875,
      "exit_price": 4144.2001953125,
      "exit_date": "2026-05-20 00:00:00+05:30",
      "exit_value": 49730.40234375,
      "profit_loss": -5342.396484375,
      "profit_loss_percent": -9.70060828222644,
      "exit_reason": "Stop Loss Hit (8%)",
      "holding_days": 29
    },
    {
      "symbol": "ABSLAMC",
      "company_name": "Aditya Birla Sun Life AMC Ltd.",
      "category": "Golden Stock",
      "entry_price": 947.0999755859375,
      "entry_date": "2026-04-06 00:00:00+05:30",
      "trendline_price": 940.8182040127841,
      "shares": 105,
      "position_value": 99445.49743652344,
      "target_price": 1136.519970703125,
      "stoploss_price": 947.0999755859375,
      "status": "closed",
      "highest_price": 1088.5999755859375,
      "exit_price": 1021.5,
      "exit_date": "2026-05-21 00:00:00+05:30",
      "exit_value": 107257.5,
      "profit_loss": 7812.0025634765625,
      "profit_loss_percent": 7.85556185533991,
      "exit_reason": "Backtest End",
      "holding_days": 45
    },
    {
      "symbol": "ATUL",
      "company_name": "Atul Ltd.",
      "category": "Golden Stock",
      "entry_price": 6149.0,
      "entry_date": "2026-04-06 00:00:00+05:30",
      "trendline_price": 6098.777777777777,
      "shares": 14,
      "position_value": 86086.0,
      "target_price": 7378.799999999999,
      "stoploss_price": 6149.0,
      "status": "closed",
      "highest_price": 7108.0,
      "exit_price": 7057.0,
      "exit_date": "2026-05-21 00:00:00+05:30",
      "exit_value": 98798.0,
      "profit_loss": 12712.0,
      "profit_loss_percent": 14.766628720117092,
      "exit_reason": "Backtest End",
      "holding_days": 45
    },
    {
      "symbol": "BEL",
      "company_name": "Bharat Electronics Ltd.",
      "category": "Golden Stock",
      "entry_price": 433.1000061035156,
      "entry_date": "2026-04-08 00:00:00+05:30",
      "trendline_price": 433.7119734859936,
      "shares": 169,
      "position_value": 73193.90103149414,
      "target_price": 519.7200073242187,
      "stoploss_price": 398.4520056152344,
      "status": "closed",
      "highest_price": 462.75,
      "exit_price": 420.3999938964844,
      "exit_date": "2026-05-21 00:00:00+05:30",
      "exit_value": 71047.59896850586,
      "profit_loss": -2146.3020629882812,
      "profit_loss_percent": -2.932350964685927,
      "exit_reason": "Backtest End",
      "holding_days": 43
    },
    {
      "symbol": "AARTIIND",
      "company_name": "Aarti Industries Ltd.",
      "category": "Golden Stock",
      "entry_price": 437.8999938964844,
      "entry_date": "2026-04-16 00:00:00+05:30",
      "trendline_price": 437.0016105405746,
      "shares": 150,
      "position_value": 65684.99908447266,
      "target_price": 525.4799926757812,
      "stoploss_price": 437.8999938964844,
      "status": "closed",
      "highest_price": 513.0999755859375,
      "exit_price": 482.75,
      "exit_date": "2026-05-21 00:00:00+05:30",
      "exit_value": 72412.5,
      "profit_loss": 6727.500915527344,
      "profit_loss_percent": 10.242065934834828,
      "exit_reason": "Backtest End",
      "holding_days": 35
    },
    {
      "symbol": "AADHARHFC",
      "company_name": "Aadhar Housing Finance Ltd.",
      "category": "Golden Stock",
      "entry_price": 498.8999938964844,
      "entry_date": "2026-05-11 00:00:00+05:30",
      "trendline_price": 499.63887193467883,
      "shares": 124,
      "position_value": 61863.59924316406,
      "target_price": 598.6799926757812,
      "stoploss_price": 458.98799438476567,
      "status": "closed",
      "highest_price": 498.8999938964844,
      "exit_price": 474.70001220703125,
      "exit_date": "2026-05-21 00:00:00+05:30",
      "exit_value": 58862.801513671875,
      "profit_loss": -3000.7977294921875,
      "profit_loss_percent": -4.850667866408979,
      "exit_reason": "Backtest End",
      "holding_days": 10
    },
    {
      "symbol": "ASTRAL",
      "company_name": "Astral Ltd.",
      "category": "Golden Stock",
      "entry_price": 1527.5999755859375,
      "entry_date": "2026-05-12 00:00:00+05:30",
      "trendline_price": 1538.3777533637153,
      "shares": 36,
      "position_value": 54993.59912109375,
      "target_price": 1833.1199707031249,
      "stoploss_price": 1405.3919775390625,
      "status": "closed",
      "highest_price": 1561.300048828125,
      "exit_price": 1480.0,
      "exit_date": "2026-05-21 00:00:00+05:30",
      "exit_value": 53280.0,
      "profit_loss": -1713.59912109375,
      "profit_loss_percent": -3.115997404207846,
      "exit_reason": "Backtest End",
      "holding_days": 9
    },
    {
      "symbol": "BAYERCROP",
      "company_name": "Bayer Cropscience Ltd.",
      "category": "Golden Stock",
      "entry_price": 4450.7001953125,
      "entry_date": "2026-05-12 00:00:00+05:30",
      "trendline_price": 4440.910807291667,
      "shares": 11,
      "position_value": 48957.7021484375,
      "target_price": 5340.840234374999,
      "stoploss_price": 4094.6441796875,
      "status": "closed",
      "highest_price": 4450.7001953125,
      "exit_price": 4323.39990234375,
      "exit_date": "2026-05-21 00:00:00+05:30",
      "exit_value": 47557.39892578125,
      "profit_loss": -1400.30322265625,
      "profit_loss_percent": -2.860230691404991,
      "exit_reason": "Backtest End",
      "holding_days": 9
    },
    {
      "symbol": "GROWW",
      "company_name": "Billionbrains Garage Ventures Ltd.",
      "category": "Golden Stock",
      "entry_price": 186.4600067138672,
      "entry_date": "2026-05-19 00:00:00+05:30",
      "trendline_price": 185.52678516932897,
      "shares": 243,
      "position_value": 45309.78163146973,
      "target_price": 223.75200805664062,
      "stoploss_price": 171.54320617675782,
      "status": "closed",
      "highest_price": 188.5,
      "exit_price": 188.3699951171875,
      "exit_date": "2026-05-21 00:00:00+05:30",
      "exit_value": 45773.90881347656,
      "profit_loss": 464.12718200683594,
      "profit_loss_percent": 1.0243421294365238,
      "exit_reason": "Backtest End",
      "holding_days": 2
    },
    {
      "symbol": "CGPOWER",
      "company_name": "CG Power and Industrial Solutions Ltd.",
      "category": "Golden Stock",
      "entry_price": 819.4000244140625,
      "entry_date": "2026-05-19 00:00:00+05:30",
      "trendline_price": 822.1184918438946,
      "shares": 49,
      "position_value": 40150.60119628906,
      "target_price": 983.280029296875,
      "stoploss_price": 753.8480224609375,
      "status": "closed",
      "highest_price": 864.9000244140625,
      "exit_price": 864.9000244140625,
      "exit_date": "2026-05-21 00:00:00+05:30",
      "exit_value": 42380.10119628906,
      "profit_loss": 2229.5,
      "profit_loss_percent": 5.552843378609391,
      "exit_reason": "Backtest End",
      "holding_days": 2
    },
    {
      "symbol": "ADANIGREEN",
      "company_name": "Adani Green Energy Ltd.",
      "category": "Golden Stock",
      "entry_price": 1363.199951171875,
      "entry_date": "2026-05-20 00:00:00+05:30",
      "trendline_price": 1367.9625244140625,
      "shares": 30,
      "position_value": 40895.99853515625,
      "target_price": 1635.8399414062499,
      "stoploss_price": 1254.1439550781251,
      "status": "closed",
      "highest_price": 1363.199951171875,
      "exit_price": 1358.199951171875,
      "exit_date": "2026-05-21 00:00:00+05:30",
      "exit_value": 40745.99853515625,
      "profit_loss": -150.0,
      "profit_loss_percent": -0.36678405069643305,
      "exit_reason": "Backtest End",
      "holding_days": 1
    }
  ]
}