[
    {
        "ticker": "EIDPARRY",
        "currentPrice": 743.4000244140625,
        "triggerPrice": 769.85,
        "distanceRemaining": -3.44,
        "fibLevelMatch": "N/A",
        "patternZone": "No Fib within 2% (closest: 78.6% at 2.0%)",
        "notificationTrigger": false,
        "positionSizing": {
            "sharesToBuy": 67,
            "strictStopLoss": 708.26,
            "pivotTargetExit": 923.82,
            "allocatedAmount": 50000.0
        },
        "wickTouches": 14,
        "timeframe": "monthly",
        "confluenceScore": 6
    },
    {
        "ticker": "RENUKA",
        "currentPrice": 23.399999618530273,
        "triggerPrice": 23.97,
        "distanceRemaining": -2.38,
        "fibLevelMatch": "N/A",
        "patternZone": "Fib confluence: 78.6% (1.9% away)",
        "notificationTrigger": false,
        "positionSizing": {
            "sharesToBuy": 2136,
            "strictStopLoss": 22.05,
            "pivotTargetExit": 28.76,
            "allocatedAmount": 50000.0
        },
        "wickTouches": 5,
        "timeframe": "monthly",
        "confluenceScore": 8
    },
    {
        "ticker": "CENTRALBK",
        "currentPrice": 30.84000015258789,
        "triggerPrice": 31.34,
        "distanceRemaining": -1.6,
        "fibLevelMatch": "N/A",
        "patternZone": "No Fib within 2% (closest: 78.6% at 3.4%)",
        "notificationTrigger": false,
        "positionSizing": {
            "sharesToBuy": 1621,
            "strictStopLoss": 28.83,
            "pivotTargetExit": 37.61,
            "allocatedAmount": 50000.0
        },
        "wickTouches": 8,
        "timeframe": "monthly",
        "confluenceScore": 6
    },
    {
        "ticker": "HAVELLS",
        "currentPrice": 1211.0,
        "triggerPrice": 1221.65,
        "distanceRemaining": -0.87,
        "fibLevelMatch": "N/A",
        "patternZone": "No Fib within 2% (closest: 78.6% at 8.7%)",
        "notificationTrigger": true,
        "positionSizing": {
            "sharesToBuy": 41,
            "strictStopLoss": 1123.92,
            "pivotTargetExit": 1465.98,
            "allocatedAmount": 50000.0
        },
        "wickTouches": 6,
        "timeframe": "monthly",
        "confluenceScore": 6
    },
    {
        "ticker": "IEX",
        "currentPrice": 126.58999633789062,
        "triggerPrice": 126.02,
        "distanceRemaining": 0.45,
        "fibLevelMatch": "N/A",
        "patternZone": "Fib confluence: 50.0% (0.7% away)",
        "notificationTrigger": true,
        "positionSizing": {
            "sharesToBuy": 394,
            "strictStopLoss": 115.93,
            "pivotTargetExit": 151.22,
            "allocatedAmount": 50000.0
        },
        "wickTouches": 10,
        "timeframe": "monthly",
        "confluenceScore": 9
    },
    {
        "ticker": "SUPREMEIND",
        "currentPrice": 3634.39990234375,
        "triggerPrice": 3524.27,
        "distanceRemaining": 3.12,
        "fibLevelMatch": "N/A",
        "patternZone": "No Fib within 2% (closest: 78.6% at 3.1%)",
        "notificationTrigger": false,
        "positionSizing": {
            "sharesToBuy": 13,
            "strictStopLoss": 3242.33,
            "pivotTargetExit": 4229.13,
            "allocatedAmount": 50000.0
        },
        "wickTouches": 13,
        "timeframe": "monthly",
        "confluenceScore": 6
    },
    {
        "ticker": "GODREJCP",
        "currentPrice": 1044.4000244140625,
        "triggerPrice": 1007.96,
        "distanceRemaining": 3.62,
        "fibLevelMatch": "N/A",
        "patternZone": "No Fib within 2% (closest: 78.6% at 6.4%)",
        "notificationTrigger": false,
        "positionSizing": {
            "sharesToBuy": 47,
            "strictStopLoss": 927.33,
            "pivotTargetExit": 1209.56,
            "allocatedAmount": 50000.0
        },
        "wickTouches": 7,
        "timeframe": "monthly",
        "confluenceScore": 6
    },
    {
        "ticker": "JYOTHYLAB",
        "currentPrice": 208.60000610351562,
        "triggerPrice": 201.27,
        "distanceRemaining": 3.64,
        "fibLevelMatch": "N/A",
        "patternZone": "No Fib within 2% (closest: 78.6% at 5.8%)",
        "notificationTrigger": false,
        "positionSizing": {
            "sharesToBuy": 239,
            "strictStopLoss": 185.17,
            "pivotTargetExit": 241.53,
            "allocatedAmount": 50000.0
        },
        "wickTouches": 6,
        "timeframe": "monthly",
        "confluenceScore": 6
    },
    {
        "ticker": "AMBUJACEM",
        "currentPrice": 459.75,
        "triggerPrice": 443.31,
        "distanceRemaining": 3.71,
        "fibLevelMatch": "N/A",
        "patternZone": "Fib confluence: 50.0% (0.1% away)",
        "notificationTrigger": false,
        "positionSizing": {
            "sharesToBuy": 108,
            "strictStopLoss": 407.84,
            "pivotTargetExit": 531.97,
            "allocatedAmount": 50000.0
        },
        "wickTouches": 9,
        "timeframe": "monthly",
        "confluenceScore": 10
    },
    {
        "ticker": "ASTRAL",
        "currentPrice": 1598.5999755859375,
        "triggerPrice": 1530.84,
        "distanceRemaining": 4.43,
        "fibLevelMatch": "N/A",
        "patternZone": "No Fib within 2% (closest: 38.2% at 2.0%)",
        "notificationTrigger": false,
        "positionSizing": {
            "sharesToBuy": 31,
            "strictStopLoss": 1408.37,
            "pivotTargetExit": 1837.0,
            "allocatedAmount": 50000.0
        },
        "wickTouches": 6,
        "timeframe": "monthly",
        "confluenceScore": 6
    },
    {
        "ticker": "BAYERCROP",
        "currentPrice": 4615.7998046875,
        "triggerPrice": 4364.58,
        "distanceRemaining": 5.76,
        "fibLevelMatch": "N/A",
        "patternZone": "Fib confluence: 78.6% (1.7% away)",
        "notificationTrigger": false,
        "positionSizing": {
            "sharesToBuy": 10,
            "strictStopLoss": 4015.41,
            "pivotTargetExit": 5237.49,
            "allocatedAmount": 50000.0
        },
        "wickTouches": 17,
        "timeframe": "monthly",
        "confluenceScore": 8
    }
]